Metadata-Version: 1.1
Name: qplots
Version: 0.7
Summary: Python package with functions for plotting
Home-page: https://github.com/AshleySetter/qplots
Author: Ashley Setter
Author-email: A.Setter@soton.ac.uk
License: UNKNOWN
Download-URL: https://github.com/AshleySetter/qplots/archive/0.7.tar.gz
Platform: UNKNOWN
